apiout/__init__.py
apiout/_version.py
apiout/cli.py
apiout/fetcher.py
apiout/generator.py
apiout/serializer.py
apiout-0.6.0.dist-info/licenses/LICENSE
apiout-0.6.0.dist-info/METADATA
apiout-0.6.0.dist-info/WHEEL
apiout-0.6.0.dist-info/entry_points.txt
apiout-0.6.0.dist-info/top_level.txt
apiout-0.6.0.dist-info/RECORD
