Metadata-Version: 2.4
Name: apiout
Version: 0.6.0
Summary: A flexible Python tool for fetching data from APIs and serializing responses using TOML configuration files
Author-email: Holger Nahrstaedt <nahrstaedt@gmail.com>
License: MIT License
Project-URL: Homepage, https://github.com/holgern/apiout
Keywords: api,json,toml,serialization,cli,http,rest
Classifier: Intended Audience :: Developers
Classifier: License :: OSI Approved :: MIT License
Classifier: Operating System :: OS Independent
Classifier: Programming Language :: Python :: 3
Classifier: Programming Language :: Python :: 3.9
Classifier: Programming Language :: Python :: 3.10
Classifier: Programming Language :: Python :: 3.11
Classifier: Programming Language :: Python :: 3.12
Classifier: Programming Language :: Python :: 3.13
Classifier: Topic :: Software Development :: Libraries
Requires-Python: >3.8.0
License-File: LICENSE
Requires-Dist: typer
Requires-Dist: rich
Requires-Dist: tomli>=1.2.0; python_version < "3.11"
Requires-Dist: pydantic>=2.0.0
Requires-Dist: httpx
Dynamic: license-file
